st_selection_header/__init__.py
st_selection_header/frontend/build/asset-manifest.json
st_selection_header/frontend/build/index.html
st_selection_header/frontend/build/static/js/2.0a2a2974.chunk.js
st_selection_header/frontend/build/static/js/2.0a2a2974.chunk.js.LICENSE.txt
st_selection_header/frontend/build/static/js/2.0a2a2974.chunk.js.map
st_selection_header/frontend/build/static/js/main.2185bd8c.chunk.js
st_selection_header/frontend/build/static/js/main.2185bd8c.chunk.js.map
st_selection_header/frontend/build/static/js/runtime-main.39defc4e.js
st_selection_header/frontend/build/static/js/runtime-main.39defc4e.js.map
st_selection_header-0.0.5.dist-info/LICENSE
st_selection_header-0.0.5.dist-info/METADATA
st_selection_header-0.0.5.dist-info/WHEEL
st_selection_header-0.0.5.dist-info/top_level.txt
st_selection_header-0.0.5.dist-info/RECORD
