Metadata-Version: 2.1
Name: st-selection-header
Version: 0.0.5
Summary: Panel for changing data
Home-page: 
Author: Elliot Glas
Author-email: elliot.glas@viscando.com
Requires-Python: >=3.6
License-File: LICENSE
Requires-Dist: streamlit (>=0.63)
